[
  {
    "shop_id": "SHOP_001",
    "shop_name": "S2クラブ石垣",
    "area": "石垣島",
    "phone_line": "0980-87-8707",
    "website": "https://www.s2club.net/",
    "operating_hours": "9:00-18:00",
    "fun_dive_available": true,
    "trial_dive_options": false,
    "license_course_available": false,
    "max_group_size": 6,
    "private_guide_available": false,
    "fun_dive_price_2tanks": 16500,
    "trial_dive_price_beach": 8000,
    "trial_dive_price_boat": 12000,
    "equipment_rental_included": false,
    "additional_fees": "",
    "safety_equipment": true,
    "insurance_coverage": true,
    "female_instructor": false,
    "english_support": false,
    "pickup_service": false,
    "beginner_friendly": true,
    "solo_welcome": false,
    "family_friendly": false,
    "photo_service": false,
    "video_service": false,
    "speciality_areas": "マンタ、自社ボート、初心者対応",
    "certification_level": "PADI",
    "experience_years": 10,
    "customer_rating": 4.9,
    "review_count": 252,
    "incident_record": "なし",
    "jiji_grade": "S级",
    "last_updated": "2025-07-07",
    "average_ratings": {
      "overall_rating": 4.9,
      "total_reviews": 252,
      "beginner_friendliness": 4.8,
      "safety_rating": 5.0,
      "instructor_rating": 4.9,
      "equipment_rating": 4.7
    },
    "reviews": [
      {
        "review_id": "REV_001",
        "reviewer_name": "田中太郎",
        "review_date": "2025-07-20",
        "overall_rating": 5,
        "review_text": "初心者でしたが、インストラクターの方が丁寧に教えてくださり、安心してマンタに出会えました！船も清潔で快適でした。",
        "helpful_count": 12,
        "beginner_friendliness": 5,
        "safety_rating": 5,
        "instructor_rating": 5,
        "equipment_rating": 4
      },
      {
        "review_id": "REV_002", 
        "reviewer_name": "山田美咲",
        "review_date": "2025-07-15",
        "overall_rating": 5,
        "review_text": "マンタポイントでの体験ダイビング、本当に感動しました！写真もたくさん撮ってもらえて最高の思い出になりました。",
        "helpful_count": 8,
        "beginner_friendliness": 5,
        "safety_rating": 5,
        "instructor_rating": 5,
        "equipment_rating": 5
      },
      {
        "review_id": "REV_003",
        "reviewer_name": "佐藤健一",
        "review_date": "2025-07-10", 
        "overall_rating": 4,
        "review_text": "ファンダイビングで利用。ガイドの知識が豊富で、普通なら見つけられない生物をたくさん見せてもらえました。",
        "helpful_count": 6,
        "beginner_friendliness": 4,
        "safety_rating": 5,
        "instructor_rating": 5,
        "equipment_rating": 4
      }
    ],
    "photos": [
      {
        "photo_id": "IMG_001",
        "url": "https://images.unsplash.com/photo-1544551763-46a013bb70d5?w=800",
        "caption": "マンタとの遭遇シーン",
        "category": "diving_scene"
      },
      {
        "photo_id": "IMG_002", 
        "url": "https://images.unsplash.com/photo-1583212292454-1fe6229603b7?w=800",
        "caption": "自社ボート外観",
        "category": "facility"
      },
      {
        "photo_id": "IMG_003",
        "url": "https://images.unsplash.com/photo-1530549387789-4c1017266635?w=800", 
        "caption": "透明度抜群の海",
        "category": "diving_scene"
      }
    ]
  },
  {
    "shop_id": "SHOP_002",
    "shop_name": "うみの教室",
    "area": "石垣島",
    "phone_line": "0980-88-2424",
    "website": "https://www.umicoza.com/",
    "operating_hours": "9:00-18:00",
    "fun_dive_available": true,
    "trial_dive_options": true,
    "license_course_available": false,
    "max_group_size": 4,
    "private_guide_available": true,
    "fun_dive_price_2tanks": 15000,
    "trial_dive_price_beach": 8000,
    "trial_dive_price_boat": 12000,
    "equipment_rental_included": false,
    "additional_fees": "",
    "safety_equipment": true,
    "insurance_coverage": true,
    "female_instructor": false,
    "english_support": false,
    "pickup_service": false,
    "beginner_friendly": true,
    "solo_welcome": false,
    "family_friendly": false,
    "photo_service": false,
    "video_service": false,
    "speciality_areas": "初心者向け、完全少人数制、体験ダイビング",
    "certification_level": "PADI",
    "experience_years": 10,
    "customer_rating": 4.8,
    "review_count": 188,
    "incident_record": "なし",
    "jiji_grade": "A级",
    "last_updated": "2025-07-07"
  },
  {
    "shop_id": "SHOP_003",
    "shop_name": "プライム・スクーバ石垣",
    "area": "石垣島",
    "phone_line": "0980-87-0839",
    "website": "https://www.primescuba-ishigaki.com/",
    "operating_hours": "9:00-18:00",
    "fun_dive_available": true,
    "trial_dive_options": false,
    "license_course_available": false,
    "max_group_size": 4,
    "private_guide_available": true,
    "fun_dive_price_2tanks": 16000,
    "trial_dive_price_beach": 8000,
    "trial_dive_price_boat": 12000,
    "equipment_rental_included": false,
    "additional_fees": "",
    "safety_equipment": true,
    "insurance_coverage": true,
    "female_instructor": false,
    "english_support": false,
    "pickup_service": false,
    "beginner_friendly": false,
    "solo_welcome": false,
    "family_friendly": false,
    "photo_service": false,
    "video_service": false,
    "speciality_areas": "マンタ、完全少人数制、上級者向け",
    "certification_level": "PADI",
    "experience_years": 10,
    "customer_rating": 5,
    "review_count": 311,
    "incident_record": "なし",
    "jiji_grade": "S级",
    "last_updated": "2025-07-07"
  },
  {
    "shop_id": "SHOP_004",
    "shop_name": "ぷしぃぬしま石垣島",
    "area": "石垣島",
    "phone_line": "0980-88-6363",
    "website": "https://www.pushynushima.com/",
    "operating_hours": "9:00-18:00",
    "fun_dive_available": true,
    "trial_dive_options": false,
    "license_course_available": false,
    "max_group_size": 6,
    "private_guide_available": false,
    "fun_dive_price_2tanks": 15400,
    "trial_dive_price_beach": 8000,
    "trial_dive_price_boat": 12000,
    "equipment_rental_included": false,
    "additional_fees": "",
    "safety_equipment": true,
    "insurance_coverage": true,
    "female_instructor": false,
    "english_support": false,
    "pickup_service": false,
    "beginner_friendly": false,
    "solo_welcome": false,
    "family_friendly": false,
    "photo_service": false,
    "video_service": false,
    "speciality_areas": "地形、マクロ、離島遠征",
    "certification_level": "PADI",
    "experience_years": 10,
    "customer_rating": 4.7,
    "review_count": 155,
    "incident_record": "なし",
    "jiji_grade": "A级",
    "last_updated": "2025-07-07"
  },
  {
    "shop_id": "SHOP_005",
    "shop_name": "サザンダイブ石垣島",
    "area": "石垣島",
    "phone_line": "0980-88-6380",
    "website": "https://www.southerndive.com/",
    "operating_hours": "9:00-18:00",
    "fun_dive_available": true,
    "trial_dive_options": false,
    "license_course_available": false,
    "max_group_size": 6,
    "private_guide_available": false,
    "fun_dive_price_2tanks": 16000,
    "trial_dive_price_beach": 8000,
    "trial_dive_price_boat": 12000,
    "equipment_rental_included": false,
    "additional_fees": "",
    "safety_equipment": true,
    "insurance_coverage": true,
    "female_instructor": false,
    "english_support": false,
    "pickup_service": false,
    "beginner_friendly": false,
    "solo_welcome": false,
    "family_friendly": false,
    "photo_service": false,
    "video_service": false,
    "speciality_areas": "マンタ、ファンダイビング専門",
    "certification_level": "PADI",
    "experience_years": 10,
    "customer_rating": 4.9,
    "review_count": 105,
    "incident_record": "なし",
    "jiji_grade": "A级",
    "last_updated": "2025-07-07"
  },
  {
    "shop_id": "SHOP_006",
    "shop_name": "ダイビングスクールてぃだ",
    "area": "石垣島",
    "phone_line": "0980-87-8414",
    "website": "https://www.tida-ishigaki.com/",
    "operating_hours": "9:00-18:00",
    "fun_dive_available": true,
    "trial_dive_options": false,
    "license_course_available": true,
    "max_group_size": 4,
    "private_guide_available": true,
    "fun_dive_price_2tanks": 14000,
    "trial_dive_price_beach": 8000,
    "trial_dive_price_boat": 12000,
    "equipment_rental_included": false,
    "additional_fees": "",
    "safety_equipment": true,
    "insurance_coverage": true,
    "female_instructor": false,
    "english_support": false,
    "pickup_service": false,
    "beginner_friendly": true,
    "solo_welcome": false,
    "family_friendly": false,
    "photo_service": false,
    "video_service": false,
    "speciality_areas": "ライセンス講習、初心者、少人数",
    "certification_level": "PADI",
    "experience_years": 10,
    "customer_rating": 4.8,
    "review_count": 92,
    "incident_record": "なし",
    "jiji_grade": "B级",
    "last_updated": "2025-07-07"
  },
  {
    "shop_id": "SHOP_007",
    "shop_name": "オールブルー石垣島",
    "area": "石垣島",
    "phone_line": "0980-82-2233",
    "website": "https://www.all-blue.net/",
    "operating_hours": "9:00-18:00",
    "fun_dive_available": true,
    "trial_dive_options": true,
    "license_course_available": false,
    "max_group_size": 6,
    "private_guide_available": false,
    "fun_dive_price_2tanks": 15000,
    "trial_dive_price_beach": 8000,
    "trial_dive_price_boat": 12000,
    "equipment_rental_included": false,
    "additional_fees": "",
    "safety_equipment": true,
    "insurance_coverage": true,
    "female_instructor": false,
    "english_support": false,
    "pickup_service": false,
    "beginner_friendly": false,
    "solo_welcome": false,
    "family_friendly": false,
    "photo_service": false,
    "video_service": false,
    "speciality_areas": "マンタ、体験ダイビング、青の洞窟",
    "certification_level": "PADI",
    "experience_years": 10,
    "customer_rating": 4.7,
    "review_count": 121,
    "incident_record": "なし",
    "jiji_grade": "A级",
    "last_updated": "2025-07-07"
  },
  {
    "shop_id": "SHOP_008",
    "shop_name": "バイキングスクーバ喜界",
    "area": "石垣島",
    "phone_line": "0980-88-2830",
    "website": "https://vikingscuba-kikai.com/",
    "operating_hours": "9:00-18:00",
    "fun_dive_available": true,
    "trial_dive_options": false,
    "license_course_available": false,
    "max_group_size": 4,
    "private_guide_available": true,
    "fun_dive_price_2tanks": 16000,
    "trial_dive_price_beach": 8000,
    "trial_dive_price_boat": 12000,
    "equipment_rental_included": false,
    "additional_fees": "",
    "safety_equipment": true,
    "insurance_coverage": true,
    "female_instructor": false,
    "english_support": false,
    "pickup_service": false,
    "beginner_friendly": false,
    "solo_welcome": false,
    "family_friendly": false,
    "photo_service": true,
    "video_service": false,
    "speciality_areas": "少人数制、のんびり、カメラ派",
    "certification_level": "PADI",
    "experience_years": 10,
    "customer_rating": 4.9,
    "review_count": 78,
    "incident_record": "なし",
    "jiji_grade": "B级",
    "last_updated": "2025-07-07"
  },
  {
    "shop_id": "SHOP_009",
    "shop_name": "ダイビングサービス大城",
    "area": "石垣島",
    "phone_line": "0980-83-2949",
    "website": "https://www.ds-oshiro.com/",
    "operating_hours": "9:00-18:00",
    "fun_dive_available": true,
    "trial_dive_options": false,
    "license_course_available": false,
    "max_group_size": 6,
    "private_guide_available": false,
    "fun_dive_price_2tanks": 15000,
    "trial_dive_price_beach": 8000,
    "trial_dive_price_boat": 12000,
    "equipment_rental_included": false,
    "additional_fees": "",
    "safety_equipment": true,
    "insurance_coverage": true,
    "female_instructor": false,
    "english_support": false,
    "pickup_service": false,
    "beginner_friendly": false,
    "solo_welcome": false,
    "family_friendly": false,
    "photo_service": false,
    "video_service": false,
    "speciality_areas": "ベテラン、昔ながら、リピーター",
    "certification_level": "PADI",
    "experience_years": 10,
    "customer_rating": 4.9,
    "review_count": 65,
    "incident_record": "なし",
    "jiji_grade": "B级",
    "last_updated": "2025-07-07"
  },
  {
    "shop_id": "SHOP_010",
    "shop_name": "Diving Shop RYAAAN",
    "area": "石垣島",
    "phone_line": "0980-87-5756",
    "website": "https://www.ryaaan.com/",
    "operating_hours": "9:00-18:00",
    "fun_dive_available": true,
    "trial_dive_options": false,
    "license_course_available": false,
    "max_group_size": 2,
    "private_guide_available": true,
    "fun_dive_price_2tanks": 18000,
    "trial_dive_price_beach": 8000,
    "trial_dive_price_boat": 12000,
    "equipment_rental_included": false,
    "additional_fees": "",
    "safety_equipment": true,
    "insurance_coverage": true,
    "female_instructor": false,
    "english_support": false,
    "pickup_service": false,
    "beginner_friendly": true,
    "solo_welcome": false,
    "family_friendly": false,
    "photo_service": false,
    "video_service": false,
    "speciality_areas": "完全貸切、プライベート、初心者",
    "certification_level": "PADI",
    "experience_years": 10,
    "customer_rating": 5,
    "review_count": 115,
    "incident_record": "なし",
    "jiji_grade": "A级",
    "last_updated": "2025-07-07"
  },
  {
    "shop_id": "SHOP_011",
    "shop_name": "Diving School 海講座",
    "area": "石垣島",
    "phone_line": "0980-83-7565",
    "website": "https://umikouza.com/",
    "operating_hours": "9:00-18:00",
    "fun_dive_available": true,
    "trial_dive_options": false,
    "license_course_available": true,
    "max_group_size": 6,
    "private_guide_available": false,
    "fun_dive_price_2tanks": 14300,
    "trial_dive_price_beach": 8000,
    "trial_dive_price_boat": 12000,
    "equipment_rental_included": false,
    "additional_fees": "",
    "safety_equipment": true,
    "insurance_coverage": true,
    "female_instructor": true,
    "english_support": false,
    "pickup_service": false,
    "beginner_friendly": true,
    "solo_welcome": false,
    "family_friendly": false,
    "photo_service": false,
    "video_service": false,
    "speciality_areas": "ライセンス講習、初心者、女性に人気",
    "certification_level": "PADI",
    "experience_years": 10,
    "customer_rating": 4.8,
    "review_count": 88,
    "incident_record": "なし",
    "jiji_grade": "B级",
    "last_updated": "2025-07-07"
  },
  {
    "shop_id": "SHOP_012",
    "shop_name": "石垣島ダイビングショップ an",
    "area": "石垣島",
    "phone_line": "0980-87-0820",
    "website": "https://an-diving.com/",
    "operating_hours": "9:00-18:00",
    "fun_dive_available": true,
    "trial_dive_options": false,
    "license_course_available": false,
    "max_group_size": 4,
    "private_guide_available": true,
    "fun_dive_price_2tanks": 15000,
    "trial_dive_price_beach": 8000,
    "trial_dive_price_boat": 12000,
    "equipment_rental_included": false,
    "additional_fees": "",
    "safety_equipment": true,
    "insurance_coverage": true,
    "female_instructor": false,
    "english_support": false,
    "pickup_service": false,
    "beginner_friendly": true,
    "solo_welcome": false,
    "family_friendly": false,
    "photo_service": false,
    "video_service": false,
    "speciality_areas": "少人数、初心者、フォト派",
    "certification_level": "PADI",
    "experience_years": 10,
    "customer_rating": 5,
    "review_count": 95,
    "incident_record": "なし",
    "jiji_grade": "B级",
    "last_updated": "2025-07-07"
  },
  {
    "shop_id": "SHOP_013",
    "shop_name": "石垣島ダイビングショップ Fun Sea",
    "area": "石垣島",
    "phone_line": "0980-88-6280",
    "website": "https://www.funsea.jp/",
    "operating_hours": "9:00-18:00",
    "fun_dive_available": true,
    "trial_dive_options": false,
    "license_course_available": false,
    "max_group_size": 6,
    "private_guide_available": false,
    "fun_dive_price_2tanks": 15000,
    "trial_dive_price_beach": 8000,
    "trial_dive_price_boat": 12000,
    "equipment_rental_included": false,
    "additional_fees": "",
    "safety_equipment": true,
    "insurance_coverage": true,
    "female_instructor": false,
    "english_support": false,
    "pickup_service": false,
    "beginner_friendly": false,
    "solo_welcome": false,
    "family_friendly": false,
    "photo_service": false,
    "video_service": false,
    "speciality_areas": "自社ボート、マンタ、地形",
    "certification_level": "PADI",
    "experience_years": 10,
    "customer_rating": 4.7,
    "review_count": 76,
    "incident_record": "なし",
    "jiji_grade": "B级",
    "last_updated": "2025-07-07"
  },
  {
    "shop_id": "SHOP_014",
    "shop_name": "マリンサービスサンフィッシュ",
    "area": "石垣島",
    "phone_line": "0980-88-2335",
    "website": "https://www.mssunfish.com/",
    "operating_hours": "9:00-18:00",
    "fun_dive_available": true,
    "trial_dive_options": true,
    "license_course_available": false,
    "max_group_size": 6,
    "private_guide_available": false,
    "fun_dive_price_2tanks": 14000,
    "trial_dive_price_beach": 8000,
    "trial_dive_price_boat": 12000,
    "equipment_rental_included": false,
    "additional_fees": "",
    "safety_equipment": true,
    "insurance_coverage": true,
    "female_instructor": false,
    "english_support": false,
    "pickup_service": false,
    "beginner_friendly": false,
    "solo_welcome": false,
    "family_friendly": false,
    "photo_service": false,
    "video_service": false,
    "speciality_areas": "マンタ、大物、体験ダイビング",
    "certification_level": "PADI",
    "experience_years": 10,
    "customer_rating": 4.6,
    "review_count": 68,
    "incident_record": "なし",
    "jiji_grade": "B级",
    "last_updated": "2025-07-07"
  },
  {
    "shop_id": "SHOP_015",
    "shop_name": "Diving Service WATANABE",
    "area": "石垣島",
    "phone_line": "0980-82-7585",
    "website": "https://dswatanabe.com/",
    "operating_hours": "9:00-18:00",
    "fun_dive_available": true,
    "trial_dive_options": false,
    "license_course_available": false,
    "max_group_size": 4,
    "private_guide_available": true,
    "fun_dive_price_2tanks": 16500,
    "trial_dive_price_beach": 8000,
    "trial_dive_price_boat": 12000,
    "equipment_rental_included": false,
    "additional_fees": "",
    "safety_equipment": true,
    "insurance_coverage": true,
    "female_instructor": false,
    "english_support": false,
    "pickup_service": false,
    "beginner_friendly": false,
    "solo_welcome": false,
    "family_friendly": false,
    "photo_service": false,
    "video_service": false,
    "speciality_areas": "少人数、ベテランガイド",
    "certification_level": "PADI",
    "experience_years": 10,
    "customer_rating": 4.9,
    "review_count": 55,
    "incident_record": "なし",
    "jiji_grade": "B级",
    "last_updated": "2025-07-07"
  },
  {
    "shop_id": "SHOP_016",
    "shop_name": "Natuxy(ナチュクシー)",
    "area": "石垣島",
    "phone_line": "0980-87-0833",
    "website": "https://natuxy.com/",
    "operating_hours": "9:00-18:00",
    "fun_dive_available": true,
    "trial_dive_options": false,
    "license_course_available": false,
    "max_group_size": 2,
    "private_guide_available": true,
    "fun_dive_price_2tanks": 16000,
    "trial_dive_price_beach": 8000,
    "trial_dive_price_boat": 12000,
    "equipment_rental_included": false,
    "additional_fees": "",
    "safety_equipment": true,
    "insurance_coverage": true,
    "female_instructor": false,
    "english_support": false,
    "pickup_service": false,
    "beginner_friendly": false,
    "solo_welcome": false,
    "family_friendly": false,
    "photo_service": false,
    "video_service": false,
    "speciality_areas": "貸切、マーメイドフォト、青の洞窟",
    "certification_level": "PADI",
    "experience_years": 10,
    "customer_rating": 5,
    "review_count": 120,
    "incident_record": "なし",
    "jiji_grade": "A级",
    "last_updated": "2025-07-07"
  },
  {
    "shop_id": "SHOP_017",
    "shop_name": "Diving Shop NOBU",
    "area": "石垣島",
    "phone_line": "0980-87-0329",
    "website": "https://www.nobuscuba-ishigaki.com/",
    "operating_hours": "9:00-18:00",
    "fun_dive_available": true,
    "trial_dive_options": false,
    "license_course_available": false,
    "max_group_size": 4,
    "private_guide_available": true,
    "fun_dive_price_2tanks": 15500,
    "trial_dive_price_beach": 8000,
    "trial_dive_price_boat": 12000,
    "equipment_rental_included": false,
    "additional_fees": "",
    "safety_equipment": true,
    "insurance_coverage": true,
    "female_instructor": false,
    "english_support": false,
    "pickup_service": false,
    "beginner_friendly": true,
    "solo_welcome": false,
    "family_friendly": false,
    "photo_service": false,
    "video_service": false,
    "speciality_areas": "少人数、カメラ、初心者",
    "certification_level": "PADI",
    "experience_years": 10,
    "customer_rating": 4.9,
    "review_count": 81,
    "incident_record": "なし",
    "jiji_grade": "B级",
    "last_updated": "2025-07-07"
  },
  {
    "shop_id": "SHOP_018",
    "shop_name": "ダイブパラッパ",
    "area": "石垣島",
    "phone_line": "0980-88-2324",
    "website": "https://www.parappa.jp/",
    "operating_hours": "9:00-18:00",
    "fun_dive_available": true,
    "trial_dive_options": false,
    "license_course_available": false,
    "max_group_size": 6,
    "private_guide_available": false,
    "fun_dive_price_2tanks": 16000,
    "trial_dive_price_beach": 8000,
    "trial_dive_price_boat": 12000,
    "equipment_rental_included": false,
    "additional_fees": "",
    "safety_equipment": true,
    "insurance_coverage": true,
    "female_instructor": false,
    "english_support": false,
    "pickup_service": false,
    "beginner_friendly": false,
    "solo_welcome": false,
    "family_friendly": false,
    "photo_service": false,
    "video_service": false,
    "speciality_areas": "のんびり、ブランクダイバー歓迎",
    "certification_level": "PADI",
    "experience_years": 10,
    "customer_rating": 4.8,
    "review_count": 60,
    "incident_record": "なし",
    "jiji_grade": "B级",
    "last_updated": "2025-07-07"
  },
  {
    "shop_id": "SHOP_019",
    "shop_name": "Diving Shop umi-cha-club",
    "area": "石垣島",
    "phone_line": "0980-88-2800",
    "website": "https://umichaclub.com/",
    "operating_hours": "9:00-18:00",
    "fun_dive_available": true,
    "trial_dive_options": true,
    "license_course_available": false,
    "max_group_size": 4,
    "private_guide_available": true,
    "fun_dive_price_2tanks": 15000,
    "trial_dive_price_beach": 8000,
    "trial_dive_price_boat": 12000,
    "equipment_rental_included": false,
    "additional_fees": "",
    "safety_equipment": true,
    "insurance_coverage": true,
    "female_instructor": false,
    "english_support": false,
    "pickup_service": false,
    "beginner_friendly": true,
    "solo_welcome": false,
    "family_friendly": false,
    "photo_service": false,
    "video_service": false,
    "speciality_areas": "完全少人数、初心者、体験",
    "certification_level": "PADI",
    "experience_years": 10,
    "customer_rating": 5,
    "review_count": 45,
    "incident_record": "なし",
    "jiji_grade": "C级",
    "last_updated": "2025-07-07"
  },
  {
    "shop_id": "SHOP_020",
    "shop_name": "ダイビングサービス海未来",
    "area": "石垣島",
    "phone_line": "0980-88-2337",
    "website": "https://www.umimiku.com/",
    "operating_hours": "9:00-18:00",
    "fun_dive_available": true,
    "trial_dive_options": false,
    "license_course_available": false,
    "max_group_size": 6,
    "private_guide_available": false,
    "fun_dive_price_2tanks": 15000,
    "trial_dive_price_beach": 8000,
    "trial_dive_price_boat": 12000,
    "equipment_rental_included": false,
    "additional_fees": "",
    "safety_equipment": true,
    "insurance_coverage": true,
    "female_instructor": false,
    "english_support": false,
    "pickup_service": false,
    "beginner_friendly": false,
    "solo_welcome": false,
    "family_friendly": false,
    "photo_service": false,
    "video_service": false,
    "speciality_areas": "マクロ、地形",
    "certification_level": "PADI",
    "experience_years": 10,
    "customer_rating": 4.7,
    "review_count": 53,
    "incident_record": "なし",
    "jiji_grade": "B级",
    "last_updated": "2025-07-07"
  },
  {
    "shop_id": "SHOP_021",
    "shop_name": "ヒートウェーブ石垣島",
    "area": "石垣島",
    "phone_line": "0980-88-5800",
    "website": "https://www.heatwave-ishigaki.com/",
    "operating_hours": "9:00-18:00",
    "fun_dive_available": true,
    "trial_dive_options": false,
    "license_course_available": false,
    "max_group_size": 6,
    "private_guide_available": false,
    "fun_dive_price_2tanks": 15400,
    "trial_dive_price_beach": 8000,
    "trial_dive_price_boat": 12000,
    "equipment_rental_included": false,
    "additional_fees": "",
    "safety_equipment": true,
    "insurance_coverage": true,
    "female_instructor": false,
    "english_support": false,
    "pickup_service": false,
    "beginner_friendly": false,
    "solo_welcome": false,
    "family_friendly": false,
    "photo_service": false,
    "video_service": false,
    "speciality_areas": "マンタ、自社ボート",
    "certification_level": "PADI",
    "experience_years": 10,
    "customer_rating": 4.6,
    "review_count": 70,
    "incident_record": "なし",
    "jiji_grade": "B级",
    "last_updated": "2025-07-07"
  },
  {
    "shop_id": "SHOP_022",
    "shop_name": "カマンタダイビングサービス",
    "area": "石垣島",
    "phone_line": "0980-88-2282",
    "website": "https://kamanta.net/",
    "operating_hours": "9:00-18:00",
    "fun_dive_available": true,
    "trial_dive_options": false,
    "license_course_available": false,
    "max_group_size": 6,
    "private_guide_available": false,
    "fun_dive_price_2tanks": 15000,
    "trial_dive_price_beach": 8000,
    "trial_dive_price_boat": 12000,
    "equipment_rental_included": false,
    "additional_fees": "",
    "safety_equipment": true,
    "insurance_coverage": true,
    "female_instructor": false,
    "english_support": false,
    "pickup_service": false,
    "beginner_friendly": false,
    "solo_welcome": false,
    "family_friendly": false,
    "photo_service": false,
    "video_service": false,
    "speciality_areas": "マンタ、川平エリア専門",
    "certification_level": "PADI",
    "experience_years": 10,
    "customer_rating": 4.9,
    "review_count": 40,
    "incident_record": "なし",
    "jiji_grade": "C级",
    "last_updated": "2025-07-07"
  },
  {
    "shop_id": "SHOP_023",
    "shop_name": "エポック石垣",
    "area": "石垣島",
    "phone_line": "0980-88-5665",
    "website": "https://www.epoch-isg.com/",
    "operating_hours": "9:00-18:00",
    "fun_dive_available": true,
    "trial_dive_options": false,
    "license_course_available": false,
    "max_group_size": 4,
    "private_guide_available": true,
    "fun_dive_price_2tanks": 14500,
    "trial_dive_price_beach": 8000,
    "trial_dive_price_boat": 12000,
    "equipment_rental_included": false,
    "additional_fees": "",
    "safety_equipment": true,
    "insurance_coverage": true,
    "female_instructor": false,
    "english_support": false,
    "pickup_service": false,
    "beginner_friendly": true,
    "solo_welcome": false,
    "family_friendly": false,
    "photo_service": false,
    "video_service": false,
    "speciality_areas": "少人数、初心者",
    "certification_level": "PADI",
    "experience_years": 10,
    "customer_rating": 4.8,
    "review_count": 35,
    "incident_record": "なし",
    "jiji_grade": "C级",
    "last_updated": "2025-07-07"
  },
  {
    "shop_id": "SHOP_024",
    "shop_name": "ダイビングサービス青い海",
    "area": "石垣島",
    "phone_line": "0980-82-0262",
    "website": "https://www.ishigaki-aoiumi.com/",
    "operating_hours": "9:00-18:00",
    "fun_dive_available": true,
    "trial_dive_options": false,
    "license_course_available": false,
    "max_group_size": 6,
    "private_guide_available": false,
    "fun_dive_price_2tanks": 14300,
    "trial_dive_price_beach": 8000,
    "trial_dive_price_boat": 12000,
    "equipment_rental_included": false,
    "additional_fees": "",
    "safety_equipment": true,
    "insurance_coverage": true,
    "female_instructor": false,
    "english_support": false,
    "pickup_service": false,
    "beginner_friendly": true,
    "solo_welcome": false,
    "family_friendly": false,
    "photo_service": false,
    "video_service": false,
    "speciality_areas": "ファンダイビング、初心者",
    "certification_level": "PADI",
    "experience_years": 10,
    "customer_rating": 4.7,
    "review_count": 48,
    "incident_record": "なし",
    "jiji_grade": "C级",
    "last_updated": "2025-07-07"
  },
  {
    "shop_id": "SHOP_025",
    "shop_name": "ゆいマーレ",
    "area": "石垣島",
    "phone_line": "0980-83-5339",
    "website": "https://www.yuimare.com/",
    "operating_hours": "9:00-18:00",
    "fun_dive_available": true,
    "trial_dive_options": true,
    "license_course_available": false,
    "max_group_size": 6,
    "private_guide_available": false,
    "fun_dive_price_2tanks": 15000,
    "trial_dive_price_beach": 8000,
    "trial_dive_price_boat": 12000,
    "equipment_rental_included": false,
    "additional_fees": "",
    "safety_equipment": true,
    "insurance_coverage": true,
    "female_instructor": false,
    "english_support": false,
    "pickup_service": false,
    "beginner_friendly": false,
    "solo_welcome": false,
    "family_friendly": false,
    "photo_service": false,
    "video_service": false,
    "speciality_areas": "体験ダイビング、シュノーケル",
    "certification_level": "PADI",
    "experience_years": 10,
    "customer_rating": 4.6,
    "review_count": 110,
    "incident_record": "なし",
    "jiji_grade": "A级",
    "last_updated": "2025-07-07"
  },
  {
    "shop_id": "SHOP_026",
    "shop_name": "シーサー石垣店",
    "area": "石垣島",
    "phone_line": "0980-88-5600",
    "website": "https://www.seasir.com/ishigaki/",
    "operating_hours": "9:00-18:00",
    "fun_dive_available": true,
    "trial_dive_options": false,
    "license_course_available": false,
    "max_group_size": 6,
    "private_guide_available": false,
    "fun_dive_price_2tanks": 16800,
    "trial_dive_price_beach": 8000,
    "trial_dive_price_boat": 12000,
    "equipment_rental_included": false,
    "additional_fees": "",
    "safety_equipment": true,
    "insurance_coverage": true,
    "female_instructor": false,
    "english_support": false,
    "pickup_service": false,
    "beginner_friendly": false,
    "solo_welcome": false,
    "family_friendly": false,
    "photo_service": false,
    "video_service": false,
    "speciality_areas": "大手、自社ボート、マンタ",
    "certification_level": "PADI",
    "experience_years": 10,
    "customer_rating": 4.5,
    "review_count": 130,
    "incident_record": "なし",
    "jiji_grade": "B级",
    "last_updated": "2025-07-07"
  },
  {
    "shop_id": "SHOP_027",
    "shop_name": "Breeze石垣島",
    "area": "石垣島",
    "phone_line": "0980-87-0865",
    "website": "https://breeze-ishigaki.jp/",
    "operating_hours": "9:00-18:00",
    "fun_dive_available": true,
    "trial_dive_options": false,
    "license_course_available": false,
    "max_group_size": 4,
    "private_guide_available": true,
    "fun_dive_price_2tanks": 16000,
    "trial_dive_price_beach": 8000,
    "trial_dive_price_boat": 12000,
    "equipment_rental_included": true,
    "additional_fees": "",
    "safety_equipment": true,
    "insurance_coverage": true,
    "female_instructor": false,
    "english_support": false,
    "pickup_service": false,
    "beginner_friendly": true,
    "solo_welcome": false,
    "family_friendly": false,
    "photo_service": false,
    "video_service": false,
    "speciality_areas": "マンタ、少人数、初心者",
    "certification_level": "PADI",
    "experience_years": 10,
    "customer_rating": 4.9,
    "review_count": 85,
    "incident_record": "なし",
    "jiji_grade": "B级",
    "last_updated": "2025-07-07"
  },
  {
    "shop_id": "SHOP_028",
    "shop_name": "Diving Shop Ryo",
    "area": "石垣島",
    "phone_line": "0980-87-8821",
    "website": "https://www.divingshop-ryo.com/",
    "operating_hours": "9:00-18:00",
    "fun_dive_available": true,
    "trial_dive_options": false,
    "license_course_available": false,
    "max_group_size": 4,
    "private_guide_available": true,
    "fun_dive_price_2tanks": 15000,
    "trial_dive_price_beach": 8000,
    "trial_dive_price_boat": 12000,
    "equipment_rental_included": false,
    "additional_fees": "",
    "safety_equipment": true,
    "insurance_coverage": true,
    "female_instructor": false,
    "english_support": false,
    "pickup_service": false,
    "beginner_friendly": true,
    "solo_welcome": false,
    "family_friendly": false,
    "photo_service": false,
    "video_service": false,
    "speciality_areas": "少人数、フォト、初心者",
    "certification_level": "PADI",
    "experience_years": 10,
    "customer_rating": 5,
    "review_count": 50,
    "incident_record": "なし",
    "jiji_grade": "B级",
    "last_updated": "2025-07-07"
  },
  {
    "shop_id": "SHOP_029",
    "shop_name": "オーシャンズ石垣島",
    "area": "石垣島",
    "phone_line": "0980-87-0830",
    "website": "https://ishigaki-oceans.com/",
    "operating_hours": "9:00-18:00",
    "fun_dive_available": true,
    "trial_dive_options": false,
    "license_course_available": false,
    "max_group_size": 6,
    "private_guide_available": false,
    "fun_dive_price_2tanks": 15500,
    "trial_dive_price_beach": 8000,
    "trial_dive_price_boat": 12000,
    "equipment_rental_included": false,
    "additional_fees": "",
    "safety_equipment": true,
    "insurance_coverage": true,
    "female_instructor": false,
    "english_support": false,
    "pickup_service": false,
    "beginner_friendly": false,
    "solo_welcome": false,
    "family_friendly": false,
    "photo_service": false,
    "video_service": false,
    "speciality_areas": "ファンダイビング、カメラ派",
    "certification_level": "PADI",
    "experience_years": 10,
    "customer_rating": 4.8,
    "review_count": 63,
    "incident_record": "なし",
    "jiji_grade": "B级",
    "last_updated": "2025-07-07"
  },
  {
    "shop_id": "SHOP_030",
    "shop_name": "スマイルフィッシュダイビング",
    "area": "石垣島",
    "phone_line": "0980-87-5939",
    "website": "https://smilefish-diving.com/",
    "operating_hours": "9:00-18:00",
    "fun_dive_available": true,
    "trial_dive_options": false,
    "license_course_available": false,
    "max_group_size": 2,
    "private_guide_available": true,
    "fun_dive_price_2tanks": 17000,
    "trial_dive_price_beach": 8000,
    "trial_dive_price_boat": 12000,
    "equipment_rental_included": false,
    "additional_fees": "",
    "safety_equipment": true,
    "insurance_coverage": true,
    "female_instructor": false,
    "english_support": false,
    "pickup_service": false,
    "beginner_friendly": true,
    "solo_welcome": false,
    "family_friendly": false,
    "photo_service": false,
    "video_service": false,
    "speciality_areas": "貸切、初心者、ファミリー",
    "certification_level": "PADI",
    "experience_years": 10,
    "customer_rating": 5,
    "review_count": 70,
    "incident_record": "なし",
    "jiji_grade": "B级",
    "last_updated": "2025-07-07"
  },
  {
    "shop_id": "SHOP_031",
    "shop_name": "HEADS石垣",
    "area": "石垣島",
    "phone_line": "0980-87-0835",
    "website": "https://www.heads-ishigaki.com/",
    "operating_hours": "9:00-18:00",
    "fun_dive_available": true,
    "trial_dive_options": false,
    "license_course_available": false,
    "max_group_size": 4,
    "private_guide_available": true,
    "fun_dive_price_2tanks": 15000,
    "trial_dive_price_beach": 8000,
    "trial_dive_price_boat": 12000,
    "equipment_rental_included": false,
    "additional_fees": "",
    "safety_equipment": true,
    "insurance_coverage": true,
    "female_instructor": false,
    "english_support": false,
    "pickup_service": false,
    "beginner_friendly": false,
    "solo_welcome": false,
    "family_friendly": false,
    "photo_service": false,
    "video_service": false,
    "speciality_areas": "少人数、リクエストベース",
    "certification_level": "PADI",
    "experience_years": 10,
    "customer_rating": 4.9,
    "review_count": 44,
    "incident_record": "なし",
    "jiji_grade": "C级",
    "last_updated": "2025-07-07"
  },
  {
    "shop_id": "SHOP_032",
    "shop_name": "ダイブステーションゆいまーる",
    "area": "石垣島",
    "phone_line": "0980-88-2082",
    "website": "https://www.ds-yuimarlu.com/",
    "operating_hours": "9:00-18:00",
    "fun_dive_available": true,
    "trial_dive_options": false,
    "license_course_available": false,
    "max_group_size": 4,
    "private_guide_available": true,
    "fun_dive_price_2tanks": 15000,
    "trial_dive_price_beach": 8000,
    "trial_dive_price_boat": 12000,
    "equipment_rental_included": false,
    "additional_fees": "",
    "safety_equipment": true,
    "insurance_coverage": true,
    "female_instructor": false,
    "english_support": false,
    "pickup_service": false,
    "beginner_friendly": false,
    "solo_welcome": false,
    "family_friendly": false,
    "photo_service": false,
    "video_service": false,
    "speciality_areas": "少人数、のんびり",
    "certification_level": "PADI",
    "experience_years": 10,
    "customer_rating": 4.8,
    "review_count": 38,
    "incident_record": "なし",
    "jiji_grade": "C级",
    "last_updated": "2025-07-07"
  },
  {
    "shop_id": "SHOP_033",
    "shop_name": "石垣島ダイビングショップ モアナ",
    "area": "石垣島",
    "phone_line": "0980-87-0337",
    "website": "https://moana-ishigaki.jp/",
    "operating_hours": "9:00-18:00",
    "fun_dive_available": true,
    "trial_dive_options": true,
    "license_course_available": false,
    "max_group_size": 2,
    "private_guide_available": true,
    "fun_dive_price_2tanks": 16500,
    "trial_dive_price_beach": 8000,
    "trial_dive_price_boat": 12000,
    "equipment_rental_included": false,
    "additional_fees": "",
    "safety_equipment": true,
    "insurance_coverage": true,
    "female_instructor": false,
    "english_support": false,
    "pickup_service": false,
    "beginner_friendly": false,
    "solo_welcome": false,
    "family_friendly": false,
    "photo_service": false,
    "video_service": false,
    "speciality_areas": "貸切、青の洞窟、体験",
    "certification_level": "PADI",
    "experience_years": 10,
    "customer_rating": 5,
    "review_count": 90,
    "incident_record": "なし",
    "jiji_grade": "B级",
    "last_updated": "2025-07-07"
  },
  {
    "shop_id": "SHOP_034",
    "shop_name": "アクロス・ダイブ",
    "area": "石垣島",
    "phone_line": "0980-88-2230",
    "website": "https://acrosdive.com/",
    "operating_hours": "9:00-18:00",
    "fun_dive_available": true,
    "trial_dive_options": false,
    "license_course_available": false,
    "max_group_size": 6,
    "private_guide_available": false,
    "fun_dive_price_2tanks": 14500,
    "trial_dive_price_beach": 8000,
    "trial_dive_price_boat": 12000,
    "equipment_rental_included": false,
    "additional_fees": "",
    "safety_equipment": true,
    "insurance_coverage": true,
    "female_instructor": false,
    "english_support": false,
    "pickup_service": false,
    "beginner_friendly": false,
    "solo_welcome": false,
    "family_friendly": false,
    "photo_service": false,
    "video_service": false,
    "speciality_areas": "ファンダイビング",
    "certification_level": "PADI",
    "experience_years": 10,
    "customer_rating": 4.7,
    "review_count": 41,
    "incident_record": "なし",
    "jiji_grade": "C级",
    "last_updated": "2025-07-07"
  },
  {
    "shop_id": "SHOP_035",
    "shop_name": "ダイビングチーム あなたの清",
    "area": "石垣島",
    "phone_line": "0980-83-1577",
    "website": "https://www.anatanokiyoshi.com/",
    "operating_hours": "9:00-18:00",
    "fun_dive_available": true,
    "trial_dive_options": false,
    "license_course_available": false,
    "max_group_size": 6,
    "private_guide_available": false,
    "fun_dive_price_2tanks": 15000,
    "trial_dive_price_beach": 8000,
    "trial_dive_price_boat": 12000,
    "equipment_rental_included": false,
    "additional_fees": "",
    "safety_equipment": true,
    "insurance_coverage": true,
    "female_instructor": false,
    "english_support": false,
    "pickup_service": false,
    "beginner_friendly": false,
    "solo_welcome": false,
    "family_friendly": false,
    "photo_service": false,
    "video_service": false,
    "speciality_areas": "ベテラン、ユニーク、お任せ",
    "certification_level": "PADI",
    "experience_years": 10,
    "customer_rating": 4.9,
    "review_count": 30,
    "incident_record": "なし",
    "jiji_grade": "C级",
    "last_updated": "2025-07-07"
  },
  {
    "shop_id": "SHOP_036",
    "shop_name": "DivingService anone",
    "area": "石垣島",
    "phone_line": "0980-87-8086",
    "website": "https://www.ds-anone.com/",
    "operating_hours": "9:00-18:00",
    "fun_dive_available": true,
    "trial_dive_options": false,
    "license_course_available": false,
    "max_group_size": 4,
    "private_guide_available": true,
    "fun_dive_price_2tanks": 16000,
    "trial_dive_price_beach": 8000,
    "trial_dive_price_boat": 12000,
    "equipment_rental_included": false,
    "additional_fees": "",
    "safety_equipment": true,
    "insurance_coverage": true,
    "female_instructor": true,
    "english_support": false,
    "pickup_service": false,
    "beginner_friendly": false,
    "solo_welcome": false,
    "family_friendly": false,
    "photo_service": false,
    "video_service": false,
    "speciality_areas": "少人数制、女性インストラクター",
    "certification_level": "PADI",
    "experience_years": 10,
    "customer_rating": 5,
    "review_count": 60,
    "incident_record": "なし",
    "jiji_grade": "B级",
    "last_updated": "2025-07-07"
  },
  {
    "shop_id": "SHOP_037",
    "shop_name": "シーフレンド",
    "area": "石垣島",
    "phone_line": "0980-82-4838",
    "website": "https://www.seafriend-ishigaki.com/",
    "operating_hours": "9:00-18:00",
    "fun_dive_available": true,
    "trial_dive_options": true,
    "license_course_available": false,
    "max_group_size": 6,
    "private_guide_available": false,
    "fun_dive_price_2tanks": 15000,
    "trial_dive_price_beach": 8000,
    "trial_dive_price_boat": 12000,
    "equipment_rental_included": false,
    "additional_fees": "",
    "safety_equipment": true,
    "insurance_coverage": true,
    "female_instructor": false,
    "english_support": false,
    "pickup_service": false,
    "beginner_friendly": false,
    "solo_welcome": false,
    "family_friendly": false,
    "photo_service": false,
    "video_service": false,
    "speciality_areas": "竹富島観光セット、体験",
    "certification_level": "PADI",
    "experience_years": 10,
    "customer_rating": 4.5,
    "review_count": 55,
    "incident_record": "なし",
    "jiji_grade": "B级",
    "last_updated": "2025-07-07"
  },
  {
    "shop_id": "SHOP_038",
    "shop_name": "ジャンキスダイビング",
    "area": "石垣島",
    "phone_line": "0980-88-2334",
    "website": "https://www.junkies-diving.com/",
    "operating_hours": "9:00-18:00",
    "fun_dive_available": true,
    "trial_dive_options": false,
    "license_course_available": false,
    "max_group_size": 4,
    "private_guide_available": true,
    "fun_dive_price_2tanks": 15500,
    "trial_dive_price_beach": 8000,
    "trial_dive_price_boat": 12000,
    "equipment_rental_included": false,
    "additional_fees": "",
    "safety_equipment": true,
    "insurance_coverage": true,
    "female_instructor": false,
    "english_support": false,
    "pickup_service": false,
    "beginner_friendly": false,
    "solo_welcome": false,
    "family_friendly": false,
    "photo_service": false,
    "video_service": false,
    "speciality_areas": "少人数、地形、マクロ",
    "certification_level": "PADI",
    "experience_years": 10,
    "customer_rating": 4.8,
    "review_count": 49,
    "incident_record": "なし",
    "jiji_grade": "C级",
    "last_updated": "2025-07-07"
  },
  {
    "shop_id": "SHOP_039",
    "shop_name": "blue space",
    "area": "石垣島",
    "phone_line": "0980-87-0331",
    "website": "https://www.blue-space.jp/",
    "operating_hours": "9:00-18:00",
    "fun_dive_available": true,
    "trial_dive_options": false,
    "license_course_available": false,
    "max_group_size": 4,
    "private_guide_available": true,
    "fun_dive_price_2tanks": 16000,
    "trial_dive_price_beach": 8000,
    "trial_dive_price_boat": 12000,
    "equipment_rental_included": false,
    "additional_fees": "",
    "safety_equipment": true,
    "insurance_coverage": true,
    "female_instructor": false,
    "english_support": false,
    "pickup_service": false,
    "beginner_friendly": true,
    "solo_welcome": false,
    "family_friendly": false,
    "photo_service": false,
    "video_service": false,
    "speciality_areas": "マンタ、少人数、初心者",
    "certification_level": "PADI",
    "experience_years": 10,
    "customer_rating": 4.9,
    "review_count": 75,
    "incident_record": "なし",
    "jiji_grade": "B级",
    "last_updated": "2025-07-07"
  },
  {
    "shop_id": "SHOP_040",
    "shop_name": "ココモ石垣島",
    "area": "石垣島",
    "phone_line": "0980-88-5858",
    "website": "https://www.cocomo-ishigaki.com/",
    "operating_hours": "9:00-18:00",
    "fun_dive_available": true,
    "trial_dive_options": true,
    "license_course_available": false,
    "max_group_size": 6,
    "private_guide_available": false,
    "fun_dive_price_2tanks": 14800,
    "trial_dive_price_beach": 8000,
    "trial_dive_price_boat": 12000,
    "equipment_rental_included": false,
    "additional_fees": "",
    "safety_equipment": true,
    "insurance_coverage": true,
    "female_instructor": false,
    "english_support": false,
    "pickup_service": false,
    "beginner_friendly": false,
    "solo_welcome": false,
    "family_friendly": false,
    "photo_service": false,
    "video_service": false,
    "speciality_areas": "体験ダイビング、幻の島",
    "certification_level": "PADI",
    "experience_years": 10,
    "customer_rating": 4.6,
    "review_count": 95,
    "incident_record": "なし",
    "jiji_grade": "B级",
    "last_updated": "2025-07-07"
  },
  {
    "shop_id": "SHOP_041",
    "shop_name": "マレア宮古島",
    "area": "宮古島",
    "phone_line": "0980-74-7033",
    "website": "https://www.marea-miyako.jp/",
    "operating_hours": "9:00-18:00",
    "fun_dive_available": true,
    "trial_dive_options": false,
    "license_course_available": false,
    "max_group_size": 6,
    "private_guide_available": false,
    "fun_dive_price_2tanks": 17600,
    "trial_dive_price_beach": 8000,
    "trial_dive_price_boat": 12000,
    "equipment_rental_included": false,
    "additional_fees": "",
    "safety_equipment": true,
    "insurance_coverage": true,
    "female_instructor": false,
    "english_support": false,
    "pickup_service": false,
    "beginner_friendly": true,
    "solo_welcome": false,
    "family_friendly": false,
    "photo_service": false,
    "video_service": false,
    "speciality_areas": "大手、自社ボート、初心者〜上級者、地形",
    "certification_level": "PADI",
    "experience_years": 10,
    "customer_rating": 4.7,
    "review_count": 155,
    "incident_record": "なし",
    "jiji_grade": "A级",
    "last_updated": "2025-07-07"
  },
  {
    "shop_id": "SHOP_042",
    "shop_name": "アイランドエキスパート宮古島",
    "area": "宮古島",
    "phone_line": "0980-74-3380",
    "website": "https://www.i-e-m.net/",
    "operating_hours": "9:00-18:00",
    "fun_dive_available": true,
    "trial_dive_options": false,
    "license_course_available": false,
    "max_group_size": 4,
    "private_guide_available": true,
    "fun_dive_price_2tanks": 16500,
    "trial_dive_price_beach": 8000,
    "trial_dive_price_boat": 12000,
    "equipment_rental_included": false,
    "additional_fees": "",
    "safety_equipment": true,
    "insurance_coverage": true,
    "female_instructor": false,
    "english_support": false,
    "pickup_service": false,
    "beginner_friendly": false,
    "solo_welcome": false,
    "family_friendly": false,
    "photo_service": false,
    "video_service": false,
    "speciality_areas": "地形専門、少人数制、上級者向け",
    "certification_level": "PADI",
    "experience_years": 10,
    "customer_rating": 4.9,
    "review_count": 92,
    "incident_record": "なし",
    "jiji_grade": "B级",
    "last_updated": "2025-07-07"
  },
  {
    "shop_id": "SHOP_043",
    "shop_name": "宮古島ダイビング AQUA",
    "area": "宮古島",
    "phone_line": "0980-76-2757",
    "website": "https://www.aqua-story.com/",
    "operating_hours": "9:00-18:00",
    "fun_dive_available": true,
    "trial_dive_options": true,
    "license_course_available": false,
    "max_group_size": 2,
    "private_guide_available": true,
    "fun_dive_price_2tanks": 15000,
    "trial_dive_price_beach": 8000,
    "trial_dive_price_boat": 12000,
    "equipment_rental_included": false,
    "additional_fees": "",
    "safety_equipment": true,
    "insurance_coverage": true,
    "female_instructor": false,
    "english_support": false,
    "pickup_service": false,
    "beginner_friendly": true,
    "solo_welcome": false,
    "family_friendly": false,
    "photo_service": false,
    "video_service": false,
    "speciality_areas": "初心者専門、体験ダイビング、完全貸切制",
    "certification_level": "PADI",
    "experience_years": 10,
    "customer_rating": 4.8,
    "review_count": 121,
    "incident_record": "なし",
    "jiji_grade": "A级",
    "last_updated": "2025-07-07"
  },
  {
    "shop_id": "SHOP_044",
    "shop_name": "BIGHOLIDAY-TRIP",
    "area": "宮古島",
    "phone_line": "0980-74-7030",
    "website": "https://www.bigholiday-trip.com/",
    "operating_hours": "9:00-18:00",
    "fun_dive_available": true,
    "trial_dive_options": false,
    "license_course_available": false,
    "max_group_size": 6,
    "private_guide_available": false,
    "fun_dive_price_2tanks": 16000,
    "trial_dive_price_beach": 8000,
    "trial_dive_price_boat": 12000,
    "equipment_rental_included": false,
    "additional_fees": "",
    "safety_equipment": true,
    "insurance_coverage": true,
    "female_instructor": false,
    "english_support": false,
    "pickup_service": false,
    "beginner_friendly": false,
    "solo_welcome": false,
    "family_friendly": false,
    "photo_service": false,
    "video_service": false,
    "speciality_areas": "八重干瀬(ヤビジ)専門、シュノーケル",
    "certification_level": "PADI",
    "experience_years": 10,
    "customer_rating": 4.7,
    "review_count": 210,
    "incident_record": "なし",
    "jiji_grade": "A级",
    "last_updated": "2025-07-07"
  },
  {
    "shop_id": "SHOP_045",
    "shop_name": "カラカラ先生のダイビングショップ",
    "area": "宮古島",
    "phone_line": "0980-73-7443",
    "website": "https://www.karakara-sensei.com/",
    "operating_hours": "9:00-18:00",
    "fun_dive_available": true,
    "trial_dive_options": false,
    "license_course_available": false,
    "max_group_size": 4,
    "private_guide_available": true,
    "fun_dive_price_2tanks": 16000,
    "trial_dive_price_beach": 8000,
    "trial_dive_price_boat": 12000,
    "equipment_rental_included": false,
    "additional_fees": "",
    "safety_equipment": true,
    "insurance_coverage": true,
    "female_instructor": false,
    "english_support": false,
    "pickup_service": false,
    "beginner_friendly": false,
    "solo_welcome": false,
    "family_friendly": false,
    "photo_service": false,
    "video_service": false,
    "speciality_areas": "少人数、のんびり、フォト派、地形",
    "certification_level": "PADI",
    "experience_years": 10,
    "customer_rating": 5,
    "review_count": 83,
    "incident_record": "なし",
    "jiji_grade": "B级",
    "last_updated": "2025-07-07"
  },
  {
    "shop_id": "SHOP_046",
    "shop_name": "カピリナ",
    "area": "宮古島",
    "phone_line": "0980-79-5991",
    "website": "https://kapilina.okinawa/",
    "operating_hours": "9:00-18:00",
    "fun_dive_available": true,
    "trial_dive_options": true,
    "license_course_available": false,
    "max_group_size": 4,
    "private_guide_available": true,
    "fun_dive_price_2tanks": 16000,
    "trial_dive_price_beach": 8000,
    "trial_dive_price_boat": 12000,
    "equipment_rental_included": false,
    "additional_fees": "",
    "safety_equipment": true,
    "insurance_coverage": true,
    "female_instructor": false,
    "english_support": false,
    "pickup_service": false,
    "beginner_friendly": true,
    "solo_welcome": false,
    "family_friendly": false,
    "photo_service": false,
    "video_service": false,
    "speciality_areas": "少人数、初心者、体験ダイビング、地形",
    "certification_level": "PADI",
    "experience_years": 10,
    "customer_rating": 5,
    "review_count": 165,
    "incident_record": "なし",
    "jiji_grade": "A级",
    "last_updated": "2025-07-07"
  },
  {
    "shop_id": "SHOP_047",
    "shop_name": "エコガイドカフェ",
    "area": "宮古島",
    "phone_line": "0980-74-7270",
    "website": "https://www.eco-guide-cafe.com/",
    "operating_hours": "9:00-18:00",
    "fun_dive_available": true,
    "trial_dive_options": false,
    "license_course_available": false,
    "max_group_size": 4,
    "private_guide_available": true,
    "fun_dive_price_2tanks": 16000,
    "trial_dive_price_beach": 8000,
    "trial_dive_price_boat": 12000,
    "equipment_rental_included": false,
    "additional_fees": "",
    "safety_equipment": true,
    "insurance_coverage": true,
    "female_instructor": false,
    "english_support": false,
    "pickup_service": false,
    "beginner_friendly": false,
    "solo_welcome": false,
    "family_friendly": false,
    "photo_service": false,
    "video_service": false,
    "speciality_areas": "少人数、エコツアー、地形",
    "certification_level": "PADI",
    "experience_years": 10,
    "customer_rating": 4.9,
    "review_count": 110,
    "incident_record": "なし",
    "jiji_grade": "A级",
    "last_updated": "2025-07-07"
  },
  {
    "shop_id": "SHOP_048",
    "shop_name": "宮古島ダイビングショップKAZA",
    "area": "宮古島",
    "phone_line": "0980-79-5639",
    "website": "https://kaza-miyako.com/",
    "operating_hours": "9:00-18:00",
    "fun_dive_available": true,
    "trial_dive_options": true,
    "license_course_available": false,
    "max_group_size": 4,
    "private_guide_available": true,
    "fun_dive_price_2tanks": 15000,
    "trial_dive_price_beach": 8000,
    "trial_dive_price_boat": 12000,
    "equipment_rental_included": false,
    "additional_fees": "",
    "safety_equipment": true,
    "insurance_coverage": true,
    "female_instructor": false,
    "english_support": false,
    "pickup_service": false,
    "beginner_friendly": true,
    "solo_welcome": false,
    "family_friendly": false,
    "photo_service": false,
    "video_service": false,
    "speciality_areas": "少人数、初心者、体験、地形",
    "certification_level": "PADI",
    "experience_years": 10,
    "customer_rating": 5,
    "review_count": 95,
    "incident_record": "なし",
    "jiji_grade": "B级",
    "last_updated": "2025-07-07"
  },
  {
    "shop_id": "SHOP_049",
    "shop_name": "Good Day",
    "area": "宮古島",
    "phone_line": "0980-79-0144",
    "website": "https://goodday-miyakojima.com/",
    "operating_hours": "9:00-18:00",
    "fun_dive_available": true,
    "trial_dive_options": true,
    "license_course_available": false,
    "max_group_size": 4,
    "private_guide_available": true,
    "fun_dive_price_2tanks": 17000,
    "trial_dive_price_beach": 8000,
    "trial_dive_price_boat": 12000,
    "equipment_rental_included": false,
    "additional_fees": "",
    "safety_equipment": true,
    "insurance_coverage": true,
    "female_instructor": false,
    "english_support": false,
    "pickup_service": false,
    "beginner_friendly": true,
    "solo_welcome": false,
    "family_friendly": false,
    "photo_service": false,
    "video_service": false,
    "speciality_areas": "少人数、初心者、体験、地形",
    "certification_level": "PADI",
    "experience_years": 10,
    "customer_rating": 5,
    "review_count": 108,
    "incident_record": "なし",
    "jiji_grade": "A级",
    "last_updated": "2025-07-07"
  },
  {
    "shop_id": "SHOP_050",
    "shop_name": "ユートピア",
    "area": "宮古島",
    "phone_line": "0980-76-2224",
    "website": "https://www.miyako-utopia.com/",
    "operating_hours": "9:00-18:00",
    "fun_dive_available": true,
    "trial_dive_options": false,
    "license_course_available": false,
    "max_group_size": 4,
    "private_guide_available": true,
    "fun_dive_price_2tanks": 15000,
    "trial_dive_price_beach": 8000,
    "trial_dive_price_boat": 12000,
    "equipment_rental_included": false,
    "additional_fees": "",
    "safety_equipment": true,
    "insurance_coverage": true,
    "female_instructor": false,
    "english_support": false,
    "pickup_service": false,
    "beginner_friendly": false,
    "solo_welcome": false,
    "family_friendly": false,
    "photo_service": false,
    "video_service": false,
    "speciality_areas": "少人数、ベテラン、地形",
    "certification_level": "PADI",
    "experience_years": 10,
    "customer_rating": 4.8,
    "review_count": 75,
    "incident_record": "なし",
    "jiji_grade": "B级",
    "last_updated": "2025-07-07"
  },
  {
    "shop_id": "SHOP_051",
    "shop_name": "日出ダイビングサービス",
    "area": "宮古島",
    "phone_line": "0980-73-6552",
    "website": "https://www.hinode-ds.com/",
    "operating_hours": "9:00-18:00",
    "fun_dive_available": true,
    "trial_dive_options": false,
    "license_course_available": false,
    "max_group_size": 4,
    "private_guide_available": true,
    "fun_dive_price_2tanks": 15000,
    "trial_dive_price_beach": 8000,
    "trial_dive_price_boat": 12000,
    "equipment_rental_included": false,
    "additional_fees": "",
    "safety_equipment": true,
    "insurance_coverage": true,
    "female_instructor": false,
    "english_support": false,
    "pickup_service": false,
    "beginner_friendly": false,
    "solo_welcome": false,
    "family_friendly": false,
    "photo_service": false,
    "video_service": false,
    "speciality_areas": "少人数、ベテラン、地形、大物",
    "certification_level": "PADI",
    "experience_years": 10,
    "customer_rating": 4.9,
    "review_count": 60,
    "incident_record": "なし",
    "jiji_grade": "B级",
    "last_updated": "2025-07-07"
  },
  {
    "shop_id": "SHOP_052",
    "shop_name": "宮古島ダイビングサポート",
    "area": "宮古島",
    "phone_line": "0980-73-8237",
    "website": "https://www.miyako-ds.com/",
    "operating_hours": "9:00-18:00",
    "fun_dive_available": true,
    "trial_dive_options": false,
    "license_course_available": false,
    "max_group_size": 4,
    "private_guide_available": true,
    "fun_dive_price_2tanks": 15000,
    "trial_dive_price_beach": 8000,
    "trial_dive_price_boat": 12000,
    "equipment_rental_included": false,
    "additional_fees": "",
    "safety_equipment": true,
    "insurance_coverage": true,
    "female_instructor": false,
    "english_support": false,
    "pickup_service": false,
    "beginner_friendly": false,
    "solo_welcome": false,
    "family_friendly": false,
    "photo_service": true,
    "video_service": false,
    "speciality_areas": "少人数、フォト派、地形",
    "certification_level": "PADI",
    "experience_years": 10,
    "customer_rating": 4.9,
    "review_count": 55,
    "incident_record": "なし",
    "jiji_grade": "B级",
    "last_updated": "2025-07-07"
  },
  {
    "shop_id": "SHOP_053",
    "shop_name": "フィッシュ・ア・ゴーゴー",
    "area": "宮古島",
    "phone_line": "0980-73-0105",
    "website": "https://www.fish-a-gogo.com/",
    "operating_hours": "9:00-18:00",
    "fun_dive_available": true,
    "trial_dive_options": false,
    "license_course_available": false,
    "max_group_size": 4,
    "private_guide_available": true,
    "fun_dive_price_2tanks": 16000,
    "trial_dive_price_beach": 8000,
    "trial_dive_price_boat": 12000,
    "equipment_rental_included": false,
    "additional_fees": "",
    "safety_equipment": true,
    "insurance_coverage": true,
    "female_instructor": false,
    "english_support": false,
    "pickup_service": false,
    "beginner_friendly": false,
    "solo_welcome": false,
    "family_friendly": false,
    "photo_service": false,
    "video_service": false,
    "speciality_areas": "少人数、リクエストベース、地形",
    "certification_level": "PADI",
    "experience_years": 10,
    "customer_rating": 4.8,
    "review_count": 68,
    "incident_record": "なし",
    "jiji_grade": "B级",
    "last_updated": "2025-07-07"
  },
  {
    "shop_id": "SHOP_054",
    "shop_name": "海のメグミ",
    "area": "宮古島",
    "phone_line": "0980-73-4567",
    "website": "https://www.uminomegumi.jp/",
    "operating_hours": "9:00-18:00",
    "fun_dive_available": true,
    "trial_dive_options": false,
    "license_course_available": false,
    "max_group_size": 4,
    "private_guide_available": true,
    "fun_dive_price_2tanks": 16000,
    "trial_dive_price_beach": 8000,
    "trial_dive_price_boat": 12000,
    "equipment_rental_included": false,
    "additional_fees": "",
    "safety_equipment": true,
    "insurance_coverage": true,
    "female_instructor": true,
    "english_support": false,
    "pickup_service": false,
    "beginner_friendly": true,
    "solo_welcome": false,
    "family_friendly": false,
    "photo_service": false,
    "video_service": false,
    "speciality_areas": "女性インストラクター、初心者、少人数",
    "certification_level": "PADI",
    "experience_years": 10,
    "customer_rating": 4.9,
    "review_count": 70,
    "incident_record": "なし",
    "jiji_grade": "B级",
    "last_updated": "2025-07-07"
  },
  {
    "shop_id": "SHOP_055",
    "shop_name": "アクアティックアドベンチャー",
    "area": "宮古島",
    "phone_line": "0980-73-3539",
    "website": "https://www.aquatic-adventure.com/",
    "operating_hours": "9:00-18:00",
    "fun_dive_available": true,
    "trial_dive_options": false,
    "license_course_available": false,
    "max_group_size": 6,
    "private_guide_available": false,
    "fun_dive_price_2tanks": 16500,
    "trial_dive_price_beach": 8000,
    "trial_dive_price_boat": 12000,
    "equipment_rental_included": false,
    "additional_fees": "",
    "safety_equipment": true,
    "insurance_coverage": true,
    "female_instructor": false,
    "english_support": false,
    "pickup_service": false,
    "beginner_friendly": false,
    "solo_welcome": false,
    "family_friendly": false,
    "photo_service": false,
    "video_service": false,
    "speciality_areas": "自社ボート、地形、大物",
    "certification_level": "PADI",
    "experience_years": 10,
    "customer_rating": 4.7,
    "review_count": 80,
    "incident_record": "なし",
    "jiji_grade": "B级",
    "last_updated": "2025-07-07"
  },
  {
    "shop_id": "SHOP_056",
    "shop_name": "サマーパーティー",
    "area": "宮古島",
    "phone_line": "0980-73-7937",
    "website": "https://www.summer-party.jp/",
    "operating_hours": "9:00-18:00",
    "fun_dive_available": true,
    "trial_dive_options": true,
    "license_course_available": false,
    "max_group_size": 6,
    "private_guide_available": false,
    "fun_dive_price_2tanks": 14000,
    "trial_dive_price_beach": 8000,
    "trial_dive_price_boat": 12000,
    "equipment_rental_included": false,
    "additional_fees": "",
    "safety_equipment": true,
    "insurance_coverage": true,
    "female_instructor": false,
    "english_support": false,
    "pickup_service": false,
    "beginner_friendly": false,
    "solo_welcome": false,
    "family_friendly": false,
    "photo_service": false,
    "video_service": false,
    "speciality_areas": "体験ダイビング、シュノーケル",
    "certification_level": "PADI",
    "experience_years": 10,
    "customer_rating": 4.8,
    "review_count": 90,
    "incident_record": "なし",
    "jiji_grade": "B级",
    "last_updated": "2025-07-07"
  },
  {
    "shop_id": "SHOP_057",
    "shop_name": "ブルーリング",
    "area": "宮古島",
    "phone_line": "0980-79-9950",
    "website": "https://bluering.jp/",
    "operating_hours": "9:00-18:00",
    "fun_dive_available": true,
    "trial_dive_options": true,
    "license_course_available": false,
    "max_group_size": 4,
    "private_guide_available": true,
    "fun_dive_price_2tanks": 16000,
    "trial_dive_price_beach": 8000,
    "trial_dive_price_boat": 12000,
    "equipment_rental_included": false,
    "additional_fees": "",
    "safety_equipment": true,
    "insurance_coverage": true,
    "female_instructor": false,
    "english_support": false,
    "pickup_service": false,
    "beginner_friendly": true,
    "solo_welcome": false,
    "family_friendly": false,
    "photo_service": false,
    "video_service": false,
    "speciality_areas": "少人数、体験ダイビング、初心者",
    "certification_level": "PADI",
    "experience_years": 10,
    "customer_rating": 5,
    "review_count": 50,
    "incident_record": "なし",
    "jiji_grade": "B级",
    "last_updated": "2025-07-07"
  },
  {
    "shop_id": "SHOP_058",
    "shop_name": "マリンハウス ”KAI”",
    "area": "宮古島",
    "phone_line": "0980-73-9252",
    "website": "https://kai-miyako.com/",
    "operating_hours": "9:00-18:00",
    "fun_dive_available": true,
    "trial_dive_options": false,
    "license_course_available": false,
    "max_group_size": 4,
    "private_guide_available": true,
    "fun_dive_price_2tanks": 15000,
    "trial_dive_price_beach": 8000,
    "trial_dive_price_boat": 12000,
    "equipment_rental_included": false,
    "additional_fees": "",
    "safety_equipment": true,
    "insurance_coverage": true,
    "female_instructor": false,
    "english_support": false,
    "pickup_service": false,
    "beginner_friendly": false,
    "solo_welcome": false,
    "family_friendly": false,
    "photo_service": false,
    "video_service": false,
    "speciality_areas": "少人数、地形、ベテラン",
    "certification_level": "PADI",
    "experience_years": 10,
    "customer_rating": 4.7,
    "review_count": 65,
    "incident_record": "なし",
    "jiji_grade": "B级",
    "last_updated": "2025-07-07"
  },
  {
    "shop_id": "SHOP_059",
    "shop_name": "24°NORTH",
    "area": "宮古島",
    "phone_line": "0980-73-7724",
    "website": "https://24-north.com/",
    "operating_hours": "9:00-18:00",
    "fun_dive_available": true,
    "trial_dive_options": false,
    "license_course_available": false,
    "max_group_size": 4,
    "private_guide_available": true,
    "fun_dive_price_2tanks": 16000,
    "trial_dive_price_beach": 8000,
    "trial_dive_price_boat": 12000,
    "equipment_rental_included": false,
    "additional_fees": "",
    "safety_equipment": true,
    "insurance_coverage": true,
    "female_instructor": false,
    "english_support": false,
    "pickup_service": false,
    "beginner_friendly": false,
    "solo_welcome": false,
    "family_friendly": false,
    "photo_service": false,
    "video_service": false,
    "speciality_areas": "少人数、地形、マクロ",
    "certification_level": "PADI",
    "experience_years": 10,
    "customer_rating": 4.8,
    "review_count": 45,
    "incident_record": "なし",
    "jiji_grade": "C级",
    "last_updated": "2025-07-07"
  },
  {
    "shop_id": "SHOP_060",
    "shop_name": "セブンシーズ",
    "area": "宮古島",
    "phone_line": "0980-75-3433",
    "website": "https://www.sevenseas-miyako.com/",
    "operating_hours": "9:00-18:00",
    "fun_dive_available": true,
    "trial_dive_options": true,
    "license_course_available": false,
    "max_group_size": 4,
    "private_guide_available": true,
    "fun_dive_price_2tanks": 16500,
    "trial_dive_price_beach": 8000,
    "trial_dive_price_boat": 12000,
    "equipment_rental_included": false,
    "additional_fees": "",
    "safety_equipment": true,
    "insurance_coverage": true,
    "female_instructor": false,
    "english_support": false,
    "pickup_service": false,
    "beginner_friendly": true,
    "solo_welcome": false,
    "family_friendly": false,
    "photo_service": false,
    "video_service": false,
    "speciality_areas": "少人数、初心者、体験、地形",
    "certification_level": "PADI",
    "experience_years": 10,
    "customer_rating": 4.9,
    "review_count": 58,
    "incident_record": "なし",
    "jiji_grade": "B级",
    "last_updated": "2025-07-07"
  },
  {
    "shop_id": "SHOP_061",
    "shop_name": "ダイビングサービスひでsun",
    "area": "宮古島",
    "phone_line": "0980-72-8882",
    "website": "https://www.hidesun.net/",
    "operating_hours": "9:00-18:00",
    "fun_dive_available": true,
    "trial_dive_options": false,
    "license_course_available": false,
    "max_group_size": 4,
    "private_guide_available": true,
    "fun_dive_price_2tanks": 15000,
    "trial_dive_price_beach": 8000,
    "trial_dive_price_boat": 12000,
    "equipment_rental_included": false,
    "additional_fees": "",
    "safety_equipment": true,
    "insurance_coverage": true,
    "female_instructor": false,
    "english_support": false,
    "pickup_service": false,
    "beginner_friendly": false,
    "solo_welcome": false,
    "family_friendly": false,
    "photo_service": false,
    "video_service": false,
    "speciality_areas": "少人数、アットホーム",
    "certification_level": "PADI",
    "experience_years": 10,
    "customer_rating": 4.9,
    "review_count": 40,
    "incident_record": "なし",
    "jiji_grade": "C级",
    "last_updated": "2025-07-07"
  },
  {
    "shop_id": "SHOP_062",
    "shop_name": "ウォーターマン",
    "area": "宮古島",
    "phone_line": "0980-75-3130",
    "website": "https://www.waterman-miyako.com/",
    "operating_hours": "9:00-18:00",
    "fun_dive_available": true,
    "trial_dive_options": false,
    "license_course_available": false,
    "max_group_size": 4,
    "private_guide_available": true,
    "fun_dive_price_2tanks": 16000,
    "trial_dive_price_beach": 8000,
    "trial_dive_price_boat": 12000,
    "equipment_rental_included": false,
    "additional_fees": "",
    "safety_equipment": true,
    "insurance_coverage": true,
    "female_instructor": false,
    "english_support": false,
    "pickup_service": false,
    "beginner_friendly": false,
    "solo_welcome": false,
    "family_friendly": false,
    "photo_service": false,
    "video_service": false,
    "speciality_areas": "少人数、地形、ワイド",
    "certification_level": "PADI",
    "experience_years": 10,
    "customer_rating": 4.8,
    "review_count": 50,
    "incident_record": "なし",
    "jiji_grade": "B级",
    "last_updated": "2025-07-07"
  },
  {
    "shop_id": "SHOP_063",
    "shop_name": "ダイビングショップ空",
    "area": "宮古島",
    "phone_line": "0980-79-0551",
    "website": "https://www.sora-miyako.com/",
    "operating_hours": "9:00-18:00",
    "fun_dive_available": true,
    "trial_dive_options": true,
    "license_course_available": false,
    "max_group_size": 4,
    "private_guide_available": true,
    "fun_dive_price_2tanks": 15000,
    "trial_dive_price_beach": 8000,
    "trial_dive_price_boat": 12000,
    "equipment_rental_included": false,
    "additional_fees": "",
    "safety_equipment": true,
    "insurance_coverage": true,
    "female_instructor": false,
    "english_support": false,
    "pickup_service": false,
    "beginner_friendly": true,
    "solo_welcome": false,
    "family_friendly": false,
    "photo_service": false,
    "video_service": false,
    "speciality_areas": "少人数、初心者、体験",
    "certification_level": "PADI",
    "experience_years": 10,
    "customer_rating": 5,
    "review_count": 35,
    "incident_record": "なし",
    "jiji_grade": "C级",
    "last_updated": "2025-07-07"
  },
  {
    "shop_id": "SHOP_064",
    "shop_name": "ヘルパーダイバーズ",
    "area": "宮古島",
    "phone_line": "0980-72-5559",
    "website": "https://www.helper-divers.com/",
    "operating_hours": "9:00-18:00",
    "fun_dive_available": true,
    "trial_dive_options": false,
    "license_course_available": false,
    "max_group_size": 4,
    "private_guide_available": true,
    "fun_dive_price_2tanks": 14000,
    "trial_dive_price_beach": 8000,
    "trial_dive_price_boat": 12000,
    "equipment_rental_included": false,
    "additional_fees": "",
    "safety_equipment": true,
    "insurance_coverage": true,
    "female_instructor": false,
    "english_support": false,
    "pickup_service": false,
    "beginner_friendly": false,
    "solo_welcome": false,
    "family_friendly": false,
    "photo_service": false,
    "video_service": false,
    "speciality_areas": "少人数、ベテラン",
    "certification_level": "PADI",
    "experience_years": 10,
    "customer_rating": 4.7,
    "review_count": 42,
    "incident_record": "なし",
    "jiji_grade": "C级",
    "last_updated": "2025-07-07"
  },
  {
    "shop_id": "SHOP_065",
    "shop_name": "アイランド・カラー",
    "area": "宮古島",
    "phone_line": "0980-75-2250",
    "website": "https://www.island-color.com/",
    "operating_hours": "9:00-18:00",
    "fun_dive_available": true,
    "trial_dive_options": false,
    "license_course_available": false,
    "max_group_size": 6,
    "private_guide_available": false,
    "fun_dive_price_2tanks": 15000,
    "trial_dive_price_beach": 8000,
    "trial_dive_price_boat": 12000,
    "equipment_rental_included": false,
    "additional_fees": "",
    "safety_equipment": true,
    "insurance_coverage": true,
    "female_instructor": false,
    "english_support": false,
    "pickup_service": false,
    "beginner_friendly": false,
    "solo_welcome": false,
    "family_friendly": false,
    "photo_service": false,
    "video_service": false,
    "speciality_areas": "シュノーケル、カヤック",
    "certification_level": "PADI",
    "experience_years": 10,
    "customer_rating": 4.8,
    "review_count": 60,
    "incident_record": "なし",
    "jiji_grade": "B级",
    "last_updated": "2025-07-07"
  },
  {
    "shop_id": "SHOP_066",
    "shop_name": "かぎすま",
    "area": "宮古島",
    "phone_line": "0980-75-4330",
    "website": "https://www.kagisuma.com/",
    "operating_hours": "9:00-18:00",
    "fun_dive_available": true,
    "trial_dive_options": false,
    "license_course_available": false,
    "max_group_size": 6,
    "private_guide_available": false,
    "fun_dive_price_2tanks": 15000,
    "trial_dive_price_beach": 8000,
    "trial_dive_price_boat": 12000,
    "equipment_rental_included": false,
    "additional_fees": "",
    "safety_equipment": true,
    "insurance_coverage": true,
    "female_instructor": false,
    "english_support": false,
    "pickup_service": false,
    "beginner_friendly": false,
    "solo_welcome": false,
    "family_friendly": false,
    "photo_service": false,
    "video_service": false,
    "speciality_areas": "八重干瀬専門、シュノーケル",
    "certification_level": "PADI",
    "experience_years": 10,
    "customer_rating": 4.9,
    "review_count": 50,
    "incident_record": "なし",
    "jiji_grade": "B级",
    "last_updated": "2025-07-07"
  },
  {
    "shop_id": "SHOP_067",
    "shop_name": "Dolphin",
    "area": "宮古島",
    "phone_line": "0980-72-9655",
    "website": "https://www.dolphin-miyako.com/",
    "operating_hours": "9:00-18:00",
    "fun_dive_available": true,
    "trial_dive_options": false,
    "license_course_available": false,
    "max_group_size": 4,
    "private_guide_available": true,
    "fun_dive_price_2tanks": 16000,
    "trial_dive_price_beach": 8000,
    "trial_dive_price_boat": 12000,
    "equipment_rental_included": false,
    "additional_fees": "",
    "safety_equipment": true,
    "insurance_coverage": true,
    "female_instructor": false,
    "english_support": false,
    "pickup_service": false,
    "beginner_friendly": false,
    "solo_welcome": false,
    "family_friendly": false,
    "photo_service": false,
    "video_service": false,
    "speciality_areas": "少人数、地形、フォト",
    "certification_level": "PADI",
    "experience_years": 10,
    "customer_rating": 4.8,
    "review_count": 48,
    "incident_record": "なし",
    "jiji_grade": "C级",
    "last_updated": "2025-07-07"
  },
  {
    "shop_id": "SHOP_068",
    "shop_name": "Southern Cross",
    "area": "宮古島",
    "phone_line": "0980-73-0402",
    "website": "https://www.southern-cross.jp/",
    "operating_hours": "9:00-18:00",
    "fun_dive_available": true,
    "trial_dive_options": false,
    "license_course_available": false,
    "max_group_size": 4,
    "private_guide_available": true,
    "fun_dive_price_2tanks": 15500,
    "trial_dive_price_beach": 8000,
    "trial_dive_price_boat": 12000,
    "equipment_rental_included": false,
    "additional_fees": "",
    "safety_equipment": true,
    "insurance_coverage": true,
    "female_instructor": false,
    "english_support": false,
    "pickup_service": false,
    "beginner_friendly": false,
    "solo_welcome": false,
    "family_friendly": false,
    "photo_service": false,
    "video_service": false,
    "speciality_areas": "少人数、ベテラン",
    "certification_level": "PADI",
    "experience_years": 10,
    "customer_rating": 4.7,
    "review_count": 55,
    "incident_record": "なし",
    "jiji_grade": "B级",
    "last_updated": "2025-07-07"
  },
  {
    "shop_id": "SHOP_069",
    "shop_name": "わとわダイビングサービス",
    "area": "宮古島",
    "phone_line": "0980-79-5775",
    "website": "https://www.watowa.net/",
    "operating_hours": "9:00-18:00",
    "fun_dive_available": true,
    "trial_dive_options": false,
    "license_course_available": false,
    "max_group_size": 4,
    "private_guide_available": true,
    "fun_dive_price_2tanks": 16000,
    "trial_dive_price_beach": 8000,
    "trial_dive_price_boat": 12000,
    "equipment_rental_included": false,
    "additional_fees": "",
    "safety_equipment": true,
    "insurance_coverage": true,
    "female_instructor": false,
    "english_support": false,
    "pickup_service": false,
    "beginner_friendly": true,
    "solo_welcome": false,
    "family_friendly": false,
    "photo_service": false,
    "video_service": false,
    "speciality_areas": "少人数、初心者、地形",
    "certification_level": "PADI",
    "experience_years": 10,
    "customer_rating": 5,
    "review_count": 45,
    "incident_record": "なし",
    "jiji_grade": "C级",
    "last_updated": "2025-07-07"
  },
  {
    "shop_id": "SHOP_070",
    "shop_name": "ダイビングショップ Breath",
    "area": "宮古島",
    "phone_line": "0980-79-9133",
    "website": "https://www.breath-miyako.com/",
    "operating_hours": "9:00-18:00",
    "fun_dive_available": true,
    "trial_dive_options": false,
    "license_course_available": false,
    "max_group_size": 4,
    "private_guide_available": true,
    "fun_dive_price_2tanks": 16500,
    "trial_dive_price_beach": 8000,
    "trial_dive_price_boat": 12000,
    "equipment_rental_included": false,
    "additional_fees": "",
    "safety_equipment": true,
    "insurance_coverage": true,
    "female_instructor": false,
    "english_support": false,
    "pickup_service": false,
    "beginner_friendly": false,
    "solo_welcome": false,
    "family_friendly": false,
    "photo_service": false,
    "video_service": false,
    "speciality_areas": "少人数、のんびり、地形",
    "certification_level": "PADI",
    "experience_years": 10,
    "customer_rating": 5,
    "review_count": 38,
    "incident_record": "なし",
    "jiji_grade": "C级",
    "last_updated": "2025-07-07"
  },
  {
    "shop_id": "SHOP_071",
    "shop_name": "宮古島ダイビングCONNECTION",
    "area": "宮古島",
    "phone_line": "0980-79-5830",
    "website": "https://www.miyako-connection.com/",
    "operating_hours": "9:00-18:00",
    "fun_dive_available": true,
    "trial_dive_options": false,
    "license_course_available": false,
    "max_group_size": 4,
    "private_guide_available": true,
    "fun_dive_price_2tanks": 16000,
    "trial_dive_price_beach": 8000,
    "trial_dive_price_boat": 12000,
    "equipment_rental_included": false,
    "additional_fees": "",
    "safety_equipment": true,
    "insurance_coverage": true,
    "female_instructor": false,
    "english_support": false,
    "pickup_service": false,
    "beginner_friendly": true,
    "solo_welcome": false,
    "family_friendly": false,
    "photo_service": false,
    "video_service": false,
    "speciality_areas": "少人数、初心者、地形",
    "certification_level": "PADI",
    "experience_years": 10,
    "customer_rating": 4.9,
    "review_count": 52,
    "incident_record": "なし",
    "jiji_grade": "B级",
    "last_updated": "2025-07-07"
  },
  {
    "shop_id": "SHOP_072",
    "shop_name": "Blue Coco",
    "area": "宮古島",
    "phone_line": "0980-79-5880",
    "website": "https://bluecoco-miyako.com/",
    "operating_hours": "9:00-18:00",
    "fun_dive_available": true,
    "trial_dive_options": true,
    "license_course_available": false,
    "max_group_size": 4,
    "private_guide_available": true,
    "fun_dive_price_2tanks": 15500,
    "trial_dive_price_beach": 8000,
    "trial_dive_price_boat": 12000,
    "equipment_rental_included": false,
    "additional_fees": "",
    "safety_equipment": true,
    "insurance_coverage": true,
    "female_instructor": false,
    "english_support": false,
    "pickup_service": false,
    "beginner_friendly": false,
    "solo_welcome": false,
    "family_friendly": false,
    "photo_service": false,
    "video_service": false,
    "speciality_areas": "少人数、体験ダイビング",
    "certification_level": "PADI",
    "experience_years": 10,
    "customer_rating": 5,
    "review_count": 40,
    "incident_record": "なし",
    "jiji_grade": "C级",
    "last_updated": "2025-07-07"
  },
  {
    "shop_id": "SHOP_073",
    "shop_name": "オーシャントライブ",
    "area": "宮古島",
    "phone_line": "0980-79-9880",
    "website": "https://ocean-tribe.jp/",
    "operating_hours": "9:00-18:00",
    "fun_dive_available": true,
    "trial_dive_options": false,
    "license_course_available": false,
    "max_group_size": 6,
    "private_guide_available": false,
    "fun_dive_price_2tanks": 15000,
    "trial_dive_price_beach": 8000,
    "trial_dive_price_boat": 12000,
    "equipment_rental_included": false,
    "additional_fees": "",
    "safety_equipment": true,
    "insurance_coverage": true,
    "female_instructor": false,
    "english_support": false,
    "pickup_service": false,
    "beginner_friendly": false,
    "solo_welcome": false,
    "family_friendly": false,
    "photo_service": false,
    "video_service": false,
    "speciality_areas": "SUP、シュノーケル",
    "certification_level": "PADI",
    "experience_years": 10,
    "customer_rating": 4.8,
    "review_count": 70,
    "incident_record": "なし",
    "jiji_grade": "B级",
    "last_updated": "2025-07-07"
  },
  {
    "shop_id": "SHOP_074",
    "shop_name": "ダイビングサービスM.O.C",
    "area": "宮古島",
    "phone_line": "0980-75-4880",
    "website": "https://www.moc-ds.com/",
    "operating_hours": "9:00-18:00",
    "fun_dive_available": true,
    "trial_dive_options": false,
    "license_course_available": false,
    "max_group_size": 4,
    "private_guide_available": true,
    "fun_dive_price_2tanks": 16000,
    "trial_dive_price_beach": 8000,
    "trial_dive_price_boat": 12000,
    "equipment_rental_included": false,
    "additional_fees": "",
    "safety_equipment": true,
    "insurance_coverage": true,
    "female_instructor": false,
    "english_support": false,
    "pickup_service": false,
    "beginner_friendly": false,
    "solo_welcome": false,
    "family_friendly": false,
    "photo_service": false,
    "video_service": false,
    "speciality_areas": "少人数、ベテラン",
    "certification_level": "PADI",
    "experience_years": 10,
    "customer_rating": 4.9,
    "review_count": 30,
    "incident_record": "なし",
    "jiji_grade": "C级",
    "last_updated": "2025-07-07"
  },
  {
    "shop_id": "SHOP_075",
    "shop_name": "海遊",
    "area": "宮古島",
    "phone_line": "0980-73-2123",
    "website": "https://www.miyakojima-kaiyu.com/",
    "operating_hours": "9:00-18:00",
    "fun_dive_available": true,
    "trial_dive_options": false,
    "license_course_available": false,
    "max_group_size": 6,
    "private_guide_available": false,
    "fun_dive_price_2tanks": 15000,
    "trial_dive_price_beach": 8000,
    "trial_dive_price_boat": 12000,
    "equipment_rental_included": false,
    "additional_fees": "",
    "safety_equipment": true,
    "insurance_coverage": true,
    "female_instructor": false,
    "english_support": false,
    "pickup_service": false,
    "beginner_friendly": false,
    "solo_welcome": false,
    "family_friendly": false,
    "photo_service": false,
    "video_service": false,
    "speciality_areas": "八重干瀬、釣り",
    "certification_level": "PADI",
    "experience_years": 10,
    "customer_rating": 4.7,
    "review_count": 65,
    "incident_record": "なし",
    "jiji_grade": "B级",
    "last_updated": "2025-07-07"
  },
  {
    "shop_id": "SHOP_076",
    "shop_name": "ネイチャー石垣島ダイビングサービス",
    "area": "石垣島",
    "phone_line": "0980-88-6100",
    "website": "https://www.nature-ishigaki.com/",
    "operating_hours": "9:00-18:00",
    "fun_dive_available": true,
    "trial_dive_options": true,
    "license_course_available": false,
    "max_group_size": 4,
    "private_guide_available": true,
    "fun_dive_price_2tanks": 15400,
    "trial_dive_price_beach": 8000,
    "trial_dive_price_boat": 12000,
    "equipment_rental_included": false,
    "additional_fees": "",
    "safety_equipment": true,
    "insurance_coverage": true,
    "female_instructor": false,
    "english_support": false,
    "pickup_service": true,
    "beginner_friendly": false,
    "solo_welcome": false,
    "family_friendly": false,
    "photo_service": false,
    "video_service": false,
    "speciality_areas": "少人数制、ファンダイビング、体験ダイビング",
    "certification_level": "PADI",
    "experience_years": 10,
    "customer_rating": 4.9,
    "review_count": 72,
    "incident_record": "なし",
    "jiji_grade": "B级",
    "last_updated": "2025-07-07"
  },
  {
    "shop_id": "SHOP_077",
    "shop_name": "石垣島ダイビングカレッジ",
    "area": "石垣島",
    "phone_line": "0980-88-5600",
    "website": "https://www.sevenseas-ishigaki.com/college.html",
    "operating_hours": "9:00-18:00",
    "fun_dive_available": true,
    "trial_dive_options": false,
    "license_course_available": true,
    "max_group_size": 6,
    "private_guide_available": false,
    "fun_dive_price_2tanks": 15000,
    "trial_dive_price_beach": 8000,
    "trial_dive_price_boat": 12000,
    "equipment_rental_included": false,
    "additional_fees": "",
    "safety_equipment": true,
    "insurance_coverage": true,
    "female_instructor": false,
    "english_support": false,
    "pickup_service": false,
    "beginner_friendly": false,
    "solo_welcome": false,
    "family_friendly": false,
    "photo_service": false,
    "video_service": false,
    "speciality_areas": "ライセンス講習専門、プロ育成(IDC)",
    "certification_level": "PADI",
    "experience_years": 10,
    "customer_rating": 4.5,
    "review_count": 133,
    "incident_record": "なし",
    "jiji_grade": "B级",
    "last_updated": "2025-07-07"
  },
  {
    "shop_id": "SHOP_078",
    "shop_name": "石垣潜水堂",
    "area": "石垣島",
    "phone_line": "0980-88-6360",
    "website": "https://www.sensuido.com/",
    "operating_hours": "9:00-18:00",
    "fun_dive_available": true,
    "trial_dive_options": false,
    "license_course_available": false,
    "max_group_size": 4,
    "private_guide_available": true,
    "fun_dive_price_2tanks": 16000,
    "trial_dive_price_beach": 8000,
    "trial_dive_price_boat": 12000,
    "equipment_rental_included": false,
    "additional_fees": "",
    "safety_equipment": true,
    "insurance_coverage": true,
    "female_instructor": false,
    "english_support": false,
    "pickup_service": false,
    "beginner_friendly": false,
    "solo_welcome": false,
    "family_friendly": false,
    "photo_service": true,
    "video_service": false,
    "speciality_areas": "1日6名限定、少人数、カメラ派、のんびり",
    "certification_level": "PADI",
    "experience_years": 10,
    "customer_rating": 4.9,
    "review_count": 51,
    "incident_record": "なし",
    "jiji_grade": "B级",
    "last_updated": "2025-07-07"
  },
  {
    "shop_id": "SHOP_079",
    "shop_name": "ダイビングサービス SUNNY SUNNY",
    "area": "石垣島",
    "phone_line": "0980-83-0785",
    "website": "https://www.sunnysunny.net/",
    "operating_hours": "9:00-18:00",
    "fun_dive_available": true,
    "trial_dive_options": false,
    "license_course_available": false,
    "max_group_size": 4,
    "private_guide_available": true,
    "fun_dive_price_2tanks": 16000,
    "trial_dive_price_beach": 8000,
    "trial_dive_price_boat": 12000,
    "equipment_rental_included": false,
    "additional_fees": "",
    "safety_equipment": true,
    "insurance_coverage": true,
    "female_instructor": false,
    "english_support": false,
    "pickup_service": false,
    "beginner_friendly": false,
    "solo_welcome": false,
    "family_friendly": false,
    "photo_service": false,
    "video_service": false,
    "speciality_areas": "少人数制、ファンダイビング、アットホーム",
    "certification_level": "PADI",
    "experience_years": 10,
    "customer_rating": 4.8,
    "review_count": 64,
    "incident_record": "なし",
    "jiji_grade": "B级",
    "last_updated": "2025-07-07"
  }
]